{"https://osgeo.geolexica.org/concepts/36/":{"http://purl.org/dc/terms/conformsTo":[{"value":"https://osgeo.geolexica.org/geolexica/v1.0/","type":"uri","graphs":["https://osgeo.geolexica.org/concepts/36/"]}],"http://purl.org/dc/terms/created":[{"value":"2022-01-20","type":"literal","datatype":"http://www.w3.org/2001/XMLSchema#date","graphs":["https://osgeo.geolexica.org/concepts/36/"]}],"http://purl.org/dc/terms/license":[{"value":"Copyright 2022 OSGeo","type":"literal","datatype":"http://www.w3.org/2001/XMLSchema#string","graphs":["https://osgeo.geolexica.org/concepts/36/"]}],"http://purl.org/dc/terms/modified":[{"value":"2022-03-25","type":"literal","datatype":"http://www.w3.org/2001/XMLSchema#date","graphs":["https://osgeo.geolexica.org/concepts/36/"]}],"http://purl.org/dc/terms/title":[{"value":"CatMDEdit","type":"literal","datatype":"http://www.w3.org/2001/XMLSchema#string","graphs":["https://osgeo.geolexica.org/concepts/36/"]}],"http://purl.org/vocab/vann/preferredNamespacePrefix":[{"value":"osgeo-concept-36","type":"literal","datatype":"http://www.w3.org/2001/XMLSchema#string","graphs":["https://osgeo.geolexica.org/concepts/36/"]}],"http://purl.org/vocab/vann/preferredNamespaceUri":[{"value":"https://osgeo.geolexica.org/concepts/36/","type":"literal","datatype":"http://www.w3.org/2001/XMLSchema#string","graphs":["https://osgeo.geolexica.org/concepts/36/"]}],"http://www.w3.org/1999/02/22-rdf-syntax-ns#type":[{"value":"http://purl.org/dc/dcmitype/Dataset","type":"uri","graphs":["https://osgeo.geolexica.org/concepts/36/"]}],"http://www.w3.org/2002/07/owl#imports":[{"value":"https://osgeo.geolexica.org/geolexica","type":"uri","graphs":["https://osgeo.geolexica.org/concepts/36/"]}]},"https://osgeo.geolexica.org/concepts/36/c36":{"http://purl.org/dc/terms/identifier":[{"value":"36","type":"literal","datatype":"http://www.w3.org/2001/XMLSchema#integer","graphs":["https://osgeo.geolexica.org/concepts/36/"]}],"http://www.w3.org/1999/02/22-rdf-syntax-ns#type":[{"value":"http://www.w3.org/2002/07/owl#NamedIndividual","type":"uri","graphs":["https://osgeo.geolexica.org/concepts/36/"]},{"value":"http://www.w3.org/2004/02/skos/core#Concept","type":"uri","graphs":["https://osgeo.geolexica.org/concepts/36/"]}],"http://www.w3.org/2000/01/rdf-schema#label":[{"value":"CatMDEdit","type":"literal","datatype":"http://www.w3.org/2001/XMLSchema#string","graphs":["https://osgeo.geolexica.org/concepts/36/"]}],"http://www.w3.org/2004/02/skos/core#definition":[{"value":"open-source computer application for creating and editing geographic metadata based upon the ISO 19115:2003 standard","type":"literal","lang":"en","graphs":["https://osgeo.geolexica.org/concepts/36/"]}],"http://www.w3.org/2004/02/skos/core#inScheme":[{"value":"https://osgeo.geolexica.org/geolexica#OSGeoConceptScheme","type":"uri","graphs":["https://osgeo.geolexica.org/concepts/36/"]}],"http://www.w3.org/2004/02/skos/core#notation":[{"value":"36","type":"literal","datatype":"http://www.w3.org/2001/XMLSchema#integer","graphs":["https://osgeo.geolexica.org/concepts/36/"]}],"http://www.w3.org/2004/02/skos/core#prefLabel":[{"value":"CatMDEdit","type":"literal","lang":"en","graphs":["https://osgeo.geolexica.org/concepts/36/"]}],"https://osgeo.geolexica.org/api/osgeo-lang#eng-note":[{"value":"Note to entry:  It is a multiplatform (Windows / UNIX) and multilingual (Spanish and English) application.","type":"literal","lang":"en","graphs":["https://osgeo.geolexica.org/concepts/36/"]}],"https://osgeo.geolexica.org/geolexica#abbreviation":[{"value":"CatMDEdit","type":"literal","datatype":"http://www.w3.org/2001/XMLSchema#string","graphs":["https://osgeo.geolexica.org/concepts/36/"]}],"https://osgeo.geolexica.org/geolexica#classification":[{"value":"preferred","type":"literal","lang":"en","graphs":["https://osgeo.geolexica.org/concepts/36/"]}],"https://osgeo.geolexica.org/geolexica#hasInfo":[{"value":"https://osgeo.geolexica.org/osgeo-info/Info36","type":"uri","graphs":["https://osgeo.geolexica.org/concepts/36/"]}],"https://osgeo.geolexica.org/geolexica#hasLDAPI":[{"value":"https://osgeo.geolexica.org/osgeo-ldapi/ldapi36-json","type":"uri","graphs":["https://osgeo.geolexica.org/concepts/36/"]},{"value":"https://osgeo.geolexica.org/osgeo-ldapi/ldapi36-jsonld","type":"uri","graphs":["https://osgeo.geolexica.org/concepts/36/"]},{"value":"https://osgeo.geolexica.org/osgeo-ldapi/ldapi36-rdfxml","type":"uri","graphs":["https://osgeo.geolexica.org/concepts/36/"]},{"value":"https://osgeo.geolexica.org/osgeo-ldapi/ldapi36-skosrdf","type":"uri","graphs":["https://osgeo.geolexica.org/concepts/36/"]}],"https://osgeo.geolexica.org/geolexica#hasOrigin":[{"value":"https://osgeo.geolexica.org/api/osgeo-lang#engRegistry","type":"uri","graphs":["https://osgeo.geolexica.org/concepts/36/"]},{"value":"https://osgeo.geolexica.org/registers/#language-eng","type":"literal","datatype":"http://www.w3.org/2001/XMLSchema#anyURI","graphs":["https://osgeo.geolexica.org/concepts/36/"]}],"https://osgeo.geolexica.org/geolexica#hasReview":[{"value":"https://osgeo.geolexica.org/osgeo-reviews/Review36","type":"uri","graphs":["https://osgeo.geolexica.org/concepts/36/"]}],"https://osgeo.geolexica.org/geolexica#hasSource":[{"value":"https://joinup.ec.europa.eu/sites/default/files/document/2011-12/gvsig-1_0-man-v1-en_01.pdf","type":"literal","datatype":"http://www.w3.org/2001/XMLSchema#string","graphs":["https://osgeo.geolexica.org/concepts/36/"]}],"https://osgeo.geolexica.org/geolexica#jsonURI":[{"value":"https://osgeo.geolexica.org/api/ldapi/36.json","type":"literal","datatype":"http://www.w3.org/2001/XMLSchema#anyURI","graphs":["https://osgeo.geolexica.org/concepts/36/"]}],"https://osgeo.geolexica.org/geolexica#jsonldURI":[{"value":"https://osgeo.geolexica.org/api/ldapi/36.jsonld","type":"literal","datatype":"http://www.w3.org/2001/XMLSchema#anyURI","graphs":["https://osgeo.geolexica.org/concepts/36/"]}],"https://osgeo.geolexica.org/geolexica#rdfxmlURI":[{"value":"https://osgeo.geolexica.org/api/ldapi/36.rdf","type":"literal","datatype":"http://www.w3.org/2001/XMLSchema#anyURI","graphs":["https://osgeo.geolexica.org/concepts/36/"]}],"https://osgeo.geolexica.org/geolexica#skosrdfURI":[{"value":"https://osgeo.geolexica.org/api/ldapi/36.ttl","type":"literal","datatype":"http://www.w3.org/2001/XMLSchema#anyURI","graphs":["https://osgeo.geolexica.org/concepts/36/"]}]}}